odoo/addons/account_invoice_tier_validation/README.rst
odoo/addons/account_invoice_tier_validation/__init__.py
odoo/addons/account_invoice_tier_validation/__manifest__.py
odoo/addons/account_invoice_tier_validation/demo/account_invoice_tier_definition.xml
odoo/addons/account_invoice_tier_validation/i18n/account_invoice_tier_validation.pot
odoo/addons/account_invoice_tier_validation/models/__init__.py
odoo/addons/account_invoice_tier_validation/models/account_invoice.py
odoo/addons/account_invoice_tier_validation/models/tier_definition.py
odoo/addons/account_invoice_tier_validation/readme/CONFIGURE.rst
odoo/addons/account_invoice_tier_validation/readme/CONTRIBUTORS.rst
odoo/addons/account_invoice_tier_validation/readme/DESCRIPTION.rst
odoo/addons/account_invoice_tier_validation/readme/USAGE.rst
odoo/addons/account_invoice_tier_validation/static/description/icon.png
odoo/addons/account_invoice_tier_validation/static/description/index.html
odoo/addons/account_invoice_tier_validation/tests/__init__.py
odoo/addons/account_invoice_tier_validation/tests/test_account_invoice_tier_validation.py
odoo/addons/account_invoice_tier_validation/views/account_invoice_view.xml
odoo11_addon_account_invoice_tier_validation-11.0.1.0.0.99.dev2.dist-info/METADATA
odoo11_addon_account_invoice_tier_validation-11.0.1.0.0.99.dev2.dist-info/WHEEL
odoo11_addon_account_invoice_tier_validation-11.0.1.0.0.99.dev2.dist-info/top_level.txt
odoo11_addon_account_invoice_tier_validation-11.0.1.0.0.99.dev2.dist-info/RECORD
