Metadata-Version: 2.1
Name: odoo11-addon-account-invoice-tier-validation
Version: 11.0.1.0.0.99.dev2
Summary: Extends the functionality of Invoice to support a tier validation process.
Home-page: https://github.com/OCA/account-invoicing
Author: ForgeFlow, Odoo Community Association (OCA)
Author-email: support@odoo-community.org
License: LGPL-3
Platform: UNKNOWN
Classifier: Programming Language :: Python
Classifier: Framework :: Odoo
Classifier: Framework :: Odoo :: 11.0
Classifier: License :: OSI Approved :: GNU Lesser General Public License v3 (LGPLv3)
Requires-Python: >=2.7, !=3.0.*, !=3.1.*, !=3.2.*, !=3.3.*, !=3.4.*
Requires-Dist: odoo11-addon-base-tier-validation
Requires-Dist: odoo <11.1dev,>=11.0a
